projeto1/__init__.py
projeto1/core.py
projeto1_package-1.0.0.dist-info/METADATA
projeto1_package-1.0.0.dist-info/WHEEL
projeto1_package-1.0.0.dist-info/top_level.txt
projeto1_package-1.0.0.dist-info/RECORD
